synqed/__init__.py
synqed/a2a_remote_agent.py
synqed/agent.py
synqed/agent_card.py
synqed/agent_factory.py
synqed/client.py
synqed/display.py
synqed/execution_engine.py
synqed/llm_utils.py
synqed/memory.py
synqed/planner.py
synqed/planner_agent.py
synqed/router.py
synqed/scheduler.py
synqed/server.py
synqed/workspace_manager.py
synqed/agent_email/__init__.py
synqed/agent_email/addressing.py
synqed/agent_email/auto_workspace.py
synqed/agent_email/main.py
synqed/agent_email/registration.py
synqed/agent_email/inbox/__init__.py
synqed/agent_email/inbox/api.py
synqed/agent_email/inbox/crypto.py
synqed/agent_email/inbox/queue.py
synqed/agent_email/inbox/rate_limiter.py
synqed/agent_email/inbox/startup.py
synqed/agent_email/inbox/worker.py
synqed/agent_email/registry/__init__.py
synqed/agent_email/registry/api.py
synqed/agent_email/registry/db.py
synqed/agent_email/registry/models.py
synqed/mdap/__init__.py
synqed/mdap/calibration.py
synqed/mdap/execution.py
synqed/mdap/red_flags.py
synqed/mdap/step_runner.py
synqed/mdap/types.py
synqed/mdap/voting.py
synqed-1.1.93.dist-info/METADATA
synqed-1.1.93.dist-info/WHEEL
synqed-1.1.93.dist-info/licenses/LICENSE
synqed-1.1.93.dist-info/RECORD
