Metadata-Version: 2.4
Name: synqed
Version: 1.1.93
Summary: Synqed - A wrapper around A2A for simplified multi-agent systems interaction and communication
Author: Synq Team
License: Proprietary
License-File: LICENSE
Requires-Python: >=3.10
Requires-Dist: a2a-sdk[http-server]==0.3.12
Requires-Dist: aiohttp>=3.8.0
Requires-Dist: cryptography>=41.0.0
Requires-Dist: httpx>=0.24.0
Requires-Dist: pydantic>=2.0.0
Requires-Dist: redis>=5.0.0
Requires-Dist: uvicorn>=0.20.0
Provides-Extra: all
Requires-Dist: a2a-sdk[all]==0.3.12; extra == 'all'
Provides-Extra: dev
Requires-Dist: mypy>=2.0.0; extra == 'dev'
Requires-Dist: pytest-asyncio>=0.21.0; extra == 'dev'
Requires-Dist: pytest-cov>=4.0.0; extra == 'dev'
Requires-Dist: pytest>=7.0.0; extra == 'dev'
Requires-Dist: ruff>=0.1.0; extra == 'dev'
Provides-Extra: grpc
Requires-Dist: a2a-sdk[grpc]==0.3.12; extra == 'grpc'
Provides-Extra: sql
Requires-Dist: a2a-sdk[sql]==0.3.12; extra == 'sql'
